jk_checkpproc/__init__.py
jk_checkpproc/bin/cli_checkpproc.py
jk_checkpproc-0.2025.8.30.dist-info/entry_points.txt
jk_checkpproc-0.2025.8.30.dist-info/licenses/LICENSE.txt
jk_checkpproc-0.2025.8.30.dist-info/WHEEL
jk_checkpproc-0.2025.8.30.dist-info/METADATA
jk_checkpproc-0.2025.8.30.dist-info/RECORD
