Metadata-Version: 2.4
Name: jk_checkpproc
Version: 0.2025.8.30
Summary: Provides a python script that checks if a specified program is a parent of the current process.
Keywords: process,shell,terminal,bash
Author-email: Jürgen Knauth <pubsrc@binary-overflow.de>
Maintainer-email: Jürgen Knauth <pubsrc@binary-overflow.de>
Requires-Python: >=3.8
Classifier: Development Status :: 5 - Production/Stable
Classifier: License :: OSI Approved :: Apache Software License
Classifier: Programming Language :: Python :: 3
License-File: LICENSE.txt
Requires-Dist: jk_sysinfo
Requires-Dist: jk_argparsing >= 0.2024.12.23
